SatanGameEngine/Colors.py
SatanGameEngine/Editor.py
SatanGameEngine/Engine.py
SatanGameEngine/GameObjects.py
SatanGameEngine/__init__.py
satan_game_engine-0.0.1.dist-info/LICENSE
satan_game_engine-0.0.1.dist-info/METADATA
satan_game_engine-0.0.1.dist-info/WHEEL
satan_game_engine-0.0.1.dist-info/top_level.txt
satan_game_engine-0.0.1.dist-info/RECORD
